{
    "category": "modern",
    "movies": [
        {
            "title": "1917",
            "director": "Sam Mendes",
            "genres": [
                "drama",
                "war"
            ],
            "year": 2019,
            "trailer": "https://www.youtube.com/watch?v=gZjQROMAh_s",
            "wiki": "https://en.wikipedia.org/wiki/1917_(2019_film)",
            "imdb": "https://www.imdb.com/title/tt8579674/",
            "rt": "https://www.rottentomatoes.com/m/1917_2019",
            "comments": "Amazing long takes",
            "tmdb": 530915,
            "production_countries": [
                {
                    "iso_3166_1": "CA",
                    "name": "Canada"
                },
                {
                    "iso_3166_1": "CN",
                    "name": "China"
                },
                {
                    "iso_3166_1": "IN",
                    "name": "India"
                },
                {
                    "iso_3166_1": "ES",
                    "name": "Spain"
                },
                {
                    "iso_3166_1": "GB",
                    "name": "United Kingdom"
                },
                {
                    "iso_3166_1": "US",
                    "name": "United States of America"
                }
            ],
            "rating_tmdb": 8.0,
            "rating_tmdb_count": 8988,
            "rating_imdb": 8.3,
            "rating_imdb_count": 512000,
            "rating_imdb_metascore": 78.0,
            "rating_imdb_critic_count": 511,
            "rating_rt_audience": 88,
            "rating_rt_tomatometer": 89
        },
        {
            "title": "The Gentleman",
            "director": "Guy Ritchie",
            "genres": [
                "action",
                "comedy",
                "crime"
            ],
            "year": 2019,
            "trailer": "https://www.youtube.com/watch?v=Ify9S7hj480",
            "wiki": "https://en.wikipedia.org/wiki/The_Gentlemen_(2019_film)",
            "imdb": "https://www.imdb.com/title/tt8367814/",
            "rt": "https://www.rottentomatoes.com/m/the_gentlemen",
            "comments": "",
            "tmdb": 522627,
            "production_countries": [
                {
                    "iso_3166_1": "GB",
                    "name": "United Kingdom"
                },
                {
                    "iso_3166_1": "US",
                    "name": "United States of America"
                }
            ],
            "rating_tmdb": 7.7,
            "rating_tmdb_count": 3761,
            "rating_imdb": 7.8,
            "rating_imdb_count": 289000,
            "rating_imdb_metascore": 51.0,
            "rating_imdb_critic_count": 291,
            "rating_rt_audience": 84,
            "rating_rt_tomatometer": 75
        },
        {
            "title": "Free State of Jones",
            "director": "Gary Ross",
            "genres": [
                "action",
                "biography",
                "drama"
            ],
            "year": 2016,
            "trailer": "https://www.youtube.com/watch?v=3EMkxEKKSQI",
            "wiki": "https://en.wikipedia.org/wiki/Free_State_of_Jones_(film)",
            "imdb": "https://www.imdb.com/title/tt1124037/",
            "rt": "https://www.rottentomatoes.com/m/free_state_of_jones",
            "comments": "",
            "tmdb": 316152,
            "production_countries": [
                {
                    "iso_3166_1": "US",
                    "name": "United States of America"
                }
            ],
            "rating_tmdb": 6.7,
            "rating_tmdb_count": 1168,
            "rating_imdb": 6.9,
            "rating_imdb_count": 56000,
            "rating_imdb_metascore": 53.0,
            "rating_imdb_critic_count": 184,
            "rating_rt_audience": 64,
            "rating_rt_tomatometer": 48
        },
        {
            "title": "Togo",
            "director": "Ericson Core",
            "genres": [
                "drama"
            ],
            "year": 2019,
            "trailer": "https://www.youtube.com/watch?v=HMfyueM-ZBQ (for dog lovers)",
            "wiki": "https://en.wikipedia.org/wiki/Togo_(film)",
            "imdb": "https://www.imdb.com/title/tt8096836/",
            "rt": "https://www.rottentomatoes.com/m/togo_2019",
            "comments": "**Willem Dafoe** FTW!",
            "tmdb": 606856,
            "production_countries": [
                {
                    "iso_3166_1": "US",
                    "name": "United States of America"
                }
            ],
            "rating_tmdb": 8.2,
            "rating_tmdb_count": 1341,
            "rating_imdb": 8.0,
            "rating_imdb_count": 44000,
            "rating_imdb_metascore": 69.0,
            "rating_imdb_critic_count": 45,
            "rating_rt_audience": 95,
            "rating_rt_tomatometer": 92
        },
        {
            "title": "Pandorum",
            "director": "Christian Alvart",
            "genres": [
                "scifi",
                "horror",
                "action & adventure"
            ],
            "year": 2006,
            "trailer": "https://www.youtube.com/watch?v=PItZ-qr9jG8",
            "wiki": "https://en.wikipedia.org/wiki/Pandorum",
            "imdb": "https://www.imdb.com/title/tt1188729/",
            "rt": "https://www.rottentomatoes.com/m/pandorum",
            "comments": "A must see for all Alien series lovers",
            "tmdb": 19898,
            "production_countries": [
                {
                    "iso_3166_1": "DE",
                    "name": "Germany"
                },
                {
                    "iso_3166_1": "GB",
                    "name": "United Kingdom"
                }
            ],
            "rating_tmdb": 6.5,
            "rating_tmdb_count": 1792,
            "rating_imdb": 6.7,
            "rating_imdb_count": 148000,
            "rating_imdb_metascore": 28.0,
            "rating_imdb_critic_count": 152,
            "rating_rt_audience": 49,
            "rating_rt_tomatometer": 30
        },
        {
            "title": "The Square",
            "director": "Ruben \u00d6stlund",
            "genres": [
                "satire",
                "drama"
            ],
            "year": 2017,
            "trailer": "https://www.youtube.com/watch?v=EUzRjRv0Ib0",
            "wiki": "https://en.wikipedia.org/wiki/The_Square_(2017_film)",
            "imdb": "https://www.imdb.com/title/tt4995790/",
            "rt": "https://www.rottentomatoes.com/m/the_square_2017",
            "comments": "",
            "tmdb": 401246,
            "production_countries": [
                {
                    "iso_3166_1": "DK",
                    "name": "Denmark"
                },
                {
                    "iso_3166_1": "FR",
                    "name": "France"
                },
                {
                    "iso_3166_1": "DE",
                    "name": "Germany"
                },
                {
                    "iso_3166_1": "SE",
                    "name": "Sweden"
                }
            ],
            "rating_tmdb": 6.8,
            "rating_tmdb_count": 1068,
            "rating_imdb": 7.2,
            "rating_imdb_count": 60000,
            "rating_imdb_metascore": 73.0,
            "rating_imdb_critic_count": 280,
            "rating_rt_audience": 71,
            "rating_rt_tomatometer": 85
        },
        {
            "title": "The Red Turtle",
            "director": "Micha\u00ebl Dudok de Wit",
            "genres": [
                "animation",
                "family",
                "fantasy"
            ],
            "year": 2016,
            "trailer": "https://www.youtube.com/watch?v=Sw7BggqBpTk",
            "wiki": "https://en.wikipedia.org/wiki/The_Red_Turtle",
            "imdb": "https://www.imdb.com/title/tt3666024/",
            "rt": "https://www.rottentomatoes.com/m/the_red_turtle",
            "comments": "",
            "tmdb": 337703,
            "production_countries": [
                {
                    "iso_3166_1": "BE",
                    "name": "Belgium"
                },
                {
                    "iso_3166_1": "FR",
                    "name": "France"
                },
                {
                    "iso_3166_1": "JP",
                    "name": "Japan"
                }
            ],
            "rating_tmdb": 7.5,
            "rating_tmdb_count": 942,
            "rating_imdb": 7.5,
            "rating_imdb_count": 34000,
            "rating_imdb_metascore": 86.0,
            "rating_imdb_critic_count": 240,
            "rating_rt_audience": 80,
            "rating_rt_tomatometer": 93
        },
        {
            "title": "November",
            "director": "Rainer Sarnet",
            "genres": [
                "drama",
                "fantasy",
                "horror"
            ],
            "year": 2017,
            "trailer": "https://www.youtube.com/watch?v=IzEcTKUHxJc&t=78s",
            "wiki": "https://en.wikipedia.org/wiki/November_(2017_film)",
            "imdb": "https://www.imdb.com/title/tt6164502/",
            "rt": "https://www.rottentomatoes.com/m/november_2018",
            "comments": "A gloomy & murky Estonian movie with fantastic camera work",
            "tmdb": 437583,
            "production_countries": [
                {
                    "iso_3166_1": "EE",
                    "name": "Estonia"
                },
                {
                    "iso_3166_1": "PL",
                    "name": "Poland"
                },
                {
                    "iso_3166_1": "NL",
                    "name": "Netherlands"
                }
            ],
            "rating_tmdb": 7.6,
            "rating_tmdb_count": 91,
            "rating_imdb": 7.2,
            "rating_imdb_count": 4000,
            "rating_imdb_metascore": 79.0,
            "rating_imdb_critic_count": 75,
            "rating_rt_audience": 74,
            "rating_rt_tomatometer": 96
        },
        {
            "title": "The Handmaiden",
            "director": "Chan-wook Park",
            "genres": [
                "drama",
                "romance",
                "thriller"
            ],
            "year": 2016,
            "trailer": "https://www.youtube.com/watch?v=whldChqCsYk",
            "wiki": "https://en.wikipedia.org/wiki/The_Handmaiden",
            "imdb": "https://www.imdb.com/title/tt4016934/",
            "rt": "https://www.rottentomatoes.com/m/the_handmaiden",
            "comments": "",
            "tmdb": 290098,
            "production_countries": [
                {
                    "iso_3166_1": "KR",
                    "name": "South Korea"
                }
            ],
            "rating_tmdb": 8.3,
            "rating_tmdb_count": 2495,
            "rating_imdb": 8.1,
            "rating_imdb_count": 131000,
            "rating_imdb_metascore": 84.0,
            "rating_imdb_critic_count": 347,
            "rating_rt_audience": 91,
            "rating_rt_tomatometer": 95
        },
        {
            "title": "Marriage Story",
            "director": "Noah Baumbach",
            "genres": [
                "comedy",
                "drama",
                "romance"
            ],
            "year": 2019,
            "trailer": "https://www.youtube.com/watch?v=BHi-a1n8t7M",
            "wiki": "https://en.wikipedia.org/wiki/Marriage_Story",
            "imdb": "https://www.imdb.com/title/tt7653254/",
            "rt": "https://www.rottentomatoes.com/m/marriage_story_2019",
            "comments": "Oh Scarlet!!!",
            "tmdb": 492188,
            "production_countries": [
                {
                    "iso_3166_1": "GB",
                    "name": "United Kingdom"
                }
            ],
            "rating_tmdb": 7.8,
            "rating_tmdb_count": 5318,
            "rating_imdb": 7.9,
            "rating_imdb_count": 280000,
            "rating_imdb_metascore": 94.0,
            "rating_imdb_critic_count": 356,
            "rating_rt_audience": 85,
            "rating_rt_tomatometer": 94
        },
        {
            "title": "Roma",
            "director": "Alfonso Cuar\u00f3n",
            "genres": [
                "social drama"
            ],
            "year": 2018,
            "trailer": "https://www.youtube.com/watch?v=6BS27ngZtxg",
            "wiki": "https://en.wikipedia.org/wiki/Roma_(2018_film)",
            "imdb": "https://www.imdb.com/title/tt6155172/",
            "rt": "https://www.rottentomatoes.com/m/roma_2018",
            "netflix": "https://www.netflix.com/gb/title/80240715",
            "comments": "",
            "tmdb": 426426,
            "production_countries": [
                {
                    "iso_3166_1": "US",
                    "name": "United States of America"
                },
                {
                    "iso_3166_1": "MX",
                    "name": "Mexico"
                }
            ],
            "rating_tmdb": 7.7,
            "rating_tmdb_count": 3264,
            "rating_imdb": 7.7,
            "rating_imdb_count": 150000,
            "rating_imdb_metascore": 96.0,
            "rating_imdb_critic_count": 423,
            "rating_rt_audience": 72,
            "rating_rt_tomatometer": 96
        },
        {
            "title": "The Bar",
            "director": "\u00c1lex de la Iglesia",
            "genres": [
                "black comedy",
                "thriller"
            ],
            "year": 2017,
            "trailer": "https://www.youtube.com/watch?v=PTazqyeYg3Y",
            "wiki": "https://en.wikipedia.org/wiki/The_Bar_(film)",
            "imdb": "https://www.imdb.com/title/tt5121816/",
            "rt": "https://www.rottentomatoes.com/m/the_bar_2017",
            "netflix": "https://www.netflix.com/gb/title/80103311",
            "comments": "",
            "tmdb": 420648,
            "production_countries": [
                {
                    "iso_3166_1": "ES",
                    "name": "Spain"
                }
            ],
            "rating_tmdb": 6.3,
            "rating_tmdb_count": 1057,
            "rating_imdb": 6.3,
            "rating_imdb_count": 25000,
            "rating_imdb_metascore": null,
            "rating_imdb_critic_count": null,
            "rating_rt_audience": 56,
            "rating_rt_tomatometer": 88
        },
        {
            "title": "La Haine",
            "director": "Mathieu Kassovitz",
            "genres": [
                "crime",
                "drama"
            ],
            "year": 1995,
            "trailer": "https://www.youtube.com/watch?v=5Hs6GwQPAQE",
            "wiki": "https://en.wikipedia.org/wiki/La_Haine",
            "imdb": "https://www.imdb.com/title/tt0113247/",
            "rt": "https://www.rottentomatoes.com/m/la_haine",
            "comments": "One of the best french movies I've ever seen",
            "tmdb": 406,
            "production_countries": [
                {
                    "iso_3166_1": "FR",
                    "name": "France"
                }
            ],
            "rating_tmdb": 8.1,
            "rating_tmdb_count": 2728,
            "rating_imdb": 8.1,
            "rating_imdb_count": 163000,
            "rating_imdb_metascore": null,
            "rating_imdb_critic_count": null,
            "rating_rt_audience": 95,
            "rating_rt_tomatometer": 100
        },
        {
            "title": "Django Unchained",
            "director": "Quentin Tarantino",
            "genres": [
                "revisionist western"
            ],
            "year": 2012,
            "trailer": "https://www.youtube.com/watch?v=_iH0UBYDI4g",
            "wiki": "https://en.wikipedia.org/wiki/Django_Unchained",
            "imdb": "https://www.imdb.com/title/tt1853728/",
            "rt": "https://www.rottentomatoes.com/m/django_unchained_2012",
            "comments": "",
            "tmdb": 68718,
            "production_countries": [
                {
                    "iso_3166_1": "US",
                    "name": "United States of America"
                }
            ],
            "rating_tmdb": 8.1,
            "rating_tmdb_count": 21648,
            "rating_imdb": 8.4,
            "rating_imdb_count": 1000000,
            "rating_imdb_metascore": 81.0,
            "rating_imdb_critic_count": 667,
            "rating_rt_audience": 91,
            "rating_rt_tomatometer": 87
        },
        {
            "title": "Beasts of the Southern Wild",
            "director": "Benh Zeitlin",
            "genres": [
                "adventure",
                "drama",
                "fantasy"
            ],
            "year": 2012,
            "trailer": "https://www.youtube.com/watch?v=pvqZzSMIZa0",
            "wiki": "https://en.wikipedia.org/wiki/Beasts_of_the_Southern_Wild",
            "imdb": "https://www.imdb.com/title/tt2125435/",
            "rt": "https://www.rottentomatoes.com/m/beasts_of_the_southern_wild",
            "netflix": "",
            "justwatch": "https://www.justwatch.com/uk/movie/beasts-of-the-southern-wild",
            "comments": "",
            "tmdb": 84175,
            "production_countries": [
                {
                    "iso_3166_1": "US",
                    "name": "United States of America"
                }
            ],
            "rating_tmdb": 6.8,
            "rating_tmdb_count": 841,
            "rating_imdb": 7.3,
            "rating_imdb_count": 82000,
            "rating_imdb_metascore": 86.0,
            "rating_imdb_critic_count": 645,
            "rating_rt_audience": 76,
            "rating_rt_tomatometer": 86
        },
        {
            "title": "The Nightingale",
            "director": "Jennifer Kent",
            "genres": [
                "adventure",
                "drama",
                "thriller"
            ],
            "year": 2018,
            "trailer": "https://www.youtube.com/watch?v=YuP8g_GQIgI",
            "wiki": "https://en.wikipedia.org/wiki/The_Nightingale_(2018_film)",
            "imdb": "https://www.imdb.com/title/tt4068576/",
            "justwatch": "https://www.justwatch.com/uk/movie/the-nightingale-2019",
            "netflix": "https://www.netflix.com/gb/title/80202703",
            "rt": "https://www.rottentomatoes.com/m/the_nightingale_2019",
            "comments": "A female Django Unchained!!!",
            "tmdb": 400090,
            "production_countries": [
                {
                    "iso_3166_1": "AU",
                    "name": "Australia"
                }
            ],
            "rating_tmdb": 7.1,
            "rating_tmdb_count": 337,
            "rating_imdb": 7.3,
            "rating_imdb_count": 27000,
            "rating_imdb_metascore": 77.0,
            "rating_imdb_critic_count": 181,
            "rating_rt_audience": 73,
            "rating_rt_tomatometer": 86
        },
        {
            "title": "Mal\u00e8na",
            "director": "Giuseppe Tornatore",
            "genres": [
                "romantic",
                "comedy",
                "drama"
            ],
            "year": 2000,
            "trailer": "https://www.youtube.com/watch?v=SxqUoUvNBXY",
            "wiki": "https://en.wikipedia.org/wiki/Mal%C3%A8na",
            "imdb": "https://www.imdb.com/title/tt0213847/",
            "justwatch": "https://www.justwatch.com/uk/movie/malena",
            "netflix": "",
            "rt": "https://www.rottentomatoes.com/m/1101561_1101561_malena",
            "comments": "",
            "tmdb": 10867,
            "production_countries": [
                {
                    "iso_3166_1": "IT",
                    "name": "Italy"
                }
            ],
            "rating_tmdb": 7.4,
            "rating_tmdb_count": 1502,
            "rating_imdb": 7.5,
            "rating_imdb_count": 98000,
            "rating_imdb_metascore": 54.0,
            "rating_imdb_critic_count": 79,
            "rating_rt_audience": 84,
            "rating_rt_tomatometer": 54
        },
        {
            "title": "The best offer",
            "director": "Giuseppe Tornatore",
            "genres": [
                "psychological thriller"
            ],
            "year": 2013,
            "trailer": "https://www.youtube.com/watch?v=r0z3TIdVPhU",
            "wiki": "https://en.wikipedia.org/wiki/The_Best_Offer",
            "imdb": "https://www.imdb.com/title/tt1924396/",
            "justwatch": "https://www.justwatch.com/uk/movie/the-best-offer",
            "netflix": "",
            "rt": "https://www.rottentomatoes.com/m/the_best_offer",
            "comments": "",
            "watched": "2021-01-28",
            "tmdb": 152742,
            "production_countries": [
                {
                    "iso_3166_1": "IT",
                    "name": "Italy"
                }
            ],
            "rating_tmdb": 7.9,
            "rating_tmdb_count": 2325,
            "rating_imdb": 7.8,
            "rating_imdb_count": 115000,
            "rating_imdb_metascore": 49.0,
            "rating_imdb_critic_count": 147,
            "rating_rt_audience": 77,
            "rating_rt_tomatometer": 56
        },
        {
            "title": "Minamata",
            "original_title": "",
            "director": "Andrew Levitas",
            "genres": [
                "drama",
                "history"
            ],
            "year": 2020,
            "trailer": "https://www.youtube.com/watch?v=Hgy3IQkd_dY",
            "wiki": "https://en.wikipedia.org/wiki/Minamata_(film)",
            "imdb": "https://www.imdb.com/title/tt9179096/",
            "rt": "https://www.rottentomatoes.com/m/minamata",
            "netflix": "",
            "justwatch": "https://www.justwatch.com/uk/movie/minamata",
            "comments": "",
            "tmdb": 560008,
            "watched": "2021-10-14",
            "production_countries": [
                {
                    "iso_3166_1": "RS",
                    "name": "Serbia"
                },
                {
                    "iso_3166_1": "AE",
                    "name": "United Arab Emirates"
                },
                {
                    "iso_3166_1": "GB",
                    "name": "United Kingdom"
                },
                {
                    "iso_3166_1": "US",
                    "name": "United States of America"
                }
            ],
            "rating_tmdb": 6.9,
            "rating_tmdb_count": 96,
            "rating_imdb": 7.7,
            "rating_imdb_count": 15000,
            "rating_imdb_metascore": 51.0,
            "rating_imdb_critic_count": 36,
            "rating_rt_audience": null,
            "rating_rt_tomatometer": 73
        }
    ]
}